uni_gzip/__init__.py
uni_gzip/exceptions.py
uni_gzip/uni_gzip.py
uni_gzip-1.1.0.dist-info/licenses/LICENSE
uni_gzip-1.1.0.dist-info/METADATA
uni_gzip-1.1.0.dist-info/WHEEL
uni_gzip-1.1.0.dist-info/top_level.txt
uni_gzip-1.1.0.dist-info/RECORD
