Metadata-Version: 2.4
Name: uni-gzip
Version: 1.1.0
Summary: A unified Python library for reading and writing gzip-compressed JSON and text files
License: MIT
Project-URL: Homepage, https://github.com/speech2srt/uni-gzip
Project-URL: Repository, https://github.com/speech2srt/uni-gzip
Project-URL: Issues, https://github.com/speech2srt/uni-gzip/issues
Requires-Python: >=3.10
License-File: LICENSE
Dynamic: license-file
